{
  "$schema": "https://raw.githubusercontent.com/martinring/tmlanguage/master/tmlanguage.json",
  "name": "JSON Script Tag",
  "scopeName": "source.json.embedded",
  "injectionSelector": "L:source.liquid",
  "patterns": [
    {
      "include": "#script-json-tag"
    }
  ],
  "repository": {
    "script-json-tag": {
      "contentName": "meta.tag.metadata.script.start.html",
      "begin": "(<)(script)\\b(?=[^>]*type=('application/(ld\\+)?json'|\"application/(ld\\+)?json\"))(?![^/>]*/>\\s*$)",
      "beginCaptures": {
        "1": {
          "name": "punctuation.definition.tag.begin.html"
        },
        "2": {
          "name": "entity.name.tag.html"
        }
      },
      "end": "(</)(script)(>)",
      "endCaptures": {
        "1": {
          "name": "punctuation.definition.tag.begin.html"
        },
        "2": {
          "name": "entity.name.tag.html"
        },
        "3": {
          "name": "punctuation.definition.tag.end.html"
        }
      },
      "patterns": [
        {
          "include": "#attribute-name"
        },
        {
          "include": "#attribute-value"
        },
        {
          "include": "#source-json"
        }
      ]
    },
    "source-json": {
      "begin": "(>)",
      "beginCaptures": {
        "0": {
          "name": "meta.tag.metadata.json.start.html"
        },
        "1": {
          "name": "punctuation.definition.tag.end.html"
        }
      },
      "end": "(?=</script>)",
      "endCaptures": {
        "0": {
          "name": "meta.tag.metadata.json.end.html"
        }
      },
      "patterns": [
        {
          "include": "source.json"
        }
      ]
    },
    "attribute-name": {
      "name": "entity.other.attribute-name.html",
      "match": "\\b([a-zA-Z\\-:_]+)"
    },
    "attribute-value": {
      "name": "string.quoted.double.html",
      "match": "(\"|').*?(\"|')"
    }
  }
}